HISTORY.txt
MANIFEST.in
README.txt
setup.cfg
setup.py
inqbus/__init__.py
inqbus.zopeftp.egg-info/PKG-INFO
inqbus.zopeftp.egg-info/SOURCES.txt
inqbus.zopeftp.egg-info/dependency_links.txt
inqbus.zopeftp.egg-info/entry_points.txt
inqbus.zopeftp.egg-info/namespace_packages.txt
inqbus.zopeftp.egg-info/not-zip-safe
inqbus.zopeftp.egg-info/requires.txt
inqbus.zopeftp.egg-info/top_level.txt
inqbus/zopeftp/__init__.py
inqbus/zopeftp/configure.zcml
inqbus/zopeftp/ftp_patch.py
inqbus/zopeftp/tests.py
inqbus/zopeftp/zope2.py