Metadata-Version: 1.0
Name: inqbus.zopeftp
Version: 1.0.1
Summary: Add a config parameter to zope.conf which allow one to configure a start path for ftp users, like the path to a plone site.
Home-page: http://svn.plone.org/svn/collective/
Author: Maik Derstappen
Author-email: maik.derstappen@inqbus.de
License: GPL
Keywords: Zope Plone FTP Zope2
Platform: UNKNOWN
Classifier: Development Status :: 5 - Production/Stable
Classifier: Environment :: Web Environment
Classifier: Intended Audience :: System Administrators
Classifier: License :: OSI Approved :: GNU General Public License (GPL)
Classifier: Programming Language :: Python
Classifier: Natural Language :: English
Classifier: Operating System :: OS Independent
Classifier: Topic :: Internet :: WWW/HTTP
Classifier: Framework :: Zope2
